{"90010":["IT","90010","Altavilla Milicia","Sicilia","SC","Palermo","PA","","","38.038","13.5495","4"],"90011":["IT","90011","Bagheria","Sicilia","SC","Palermo","PA","","","38.0789","13.5124","4"],"90012":["IT","90012","San Giovanni Li Greci","Sicilia","SC","Palermo","PA","","","37.9017","13.6525","3"],"90013":["IT","90013","Castelbuono","Sicilia","SC","Palermo","PA","","","37.9253","14.0867","4"],"90014":["IT","90014","Casteldaccia","Sicilia","SC","Palermo","PA","","","38.0512","13.5304","4"],"90015":["IT","90015","Sant'Ambrogio","Sicilia","SC","Palermo","PA","","","38.0187","14.0878","4"],"90016":["IT","90016","Collesano","Sicilia","SC","Palermo","PA","","","37.9181","13.937","4"],"90017":["IT","90017","Sant'Elia","Sicilia","SC","Palermo","PA","","","38.0964","13.5376","4"],"90018":["IT","90018","Danigarci","Sicilia","SC","Palermo","PA","","","37.9823","13.6973","3"],"90019":["IT","90019","San Nicolo' L'Arena","Sicilia","SC","Palermo","PA","","","38.0042","13.6339","3"],"90020":["IT","90020","Castellana Sicula","Sicilia","SC","Palermo","PA","","","37.7869","14.0391","4"],"90021":["IT","90021","Alia","Sicilia","SC","Palermo","PA","","","37.7787","13.7139","4"],"90022":["IT","90022","Caltavuturo","Sicilia","SC","Palermo","PA","","","37.8204","13.8916","4"],"90023":["IT","90023","Ciminna","Sicilia","SC","Palermo","PA","","","37.8976","13.5597","4"],"90024":["IT","90024","Gangi","Sicilia","SC","Palermo","PA","","","37.7957","14.2044","4"],"90025":["IT","90025","Lercara Friddi","Sicilia","SC","Palermo","PA","","","37.7466","13.6039","4"],"90026":["IT","90026","Pianello Di Petralia Sottana","Sicilia","SC","Palermo","PA","","","37.7871","14.1124","3"],"90027":["IT","90027","Petralia Sottana","Sicilia","SC","Palermo","PA","","","37.8092","14.0929","4"],"90028":["IT","90028","Polizzi Generosa","Sicilia","SC","Palermo","PA","","","37.8116","14.0027","4"],"90029":["IT","90029","Valledolmo","Sicilia","SC","Palermo","PA","","","37.747","13.8281","4"],"90030":["IT","90030","Giuliana","Sicilia","SC","Palermo","PA","","","37.6728","13.2374","4"],"90031":["IT","90031","Belmonte Mezzagno","Sicilia","SC","Palermo","PA","","","38.0465","13.3921","4"],"90032":["IT","90032","Bisacquino","Sicilia","SC","Palermo","PA","","","37.7035","13.2605","4"],"90033":["IT","90033","Chiusa Sclafani","Sicilia","SC","Palermo","PA","","","37.6769","13.2707","4"],"90034":["IT","90034","Ficuzza","Sicilia","SC","Palermo","PA","","","37.8849","13.3754","4"],"90035":["IT","90035","Marineo","Sicilia","SC","Palermo","PA","","","37.9519","13.4178","4"],"90036":["IT","90036","Portella Di Mare","Sicilia","SC","Palermo","PA","","","38.073","13.462","4"],"90037":["IT","90037","Piana Degli Albanesi","Sicilia","SC","Palermo","PA","","","37.9937","13.2846","4"],"90038":["IT","90038","Prizzi","Sicilia","SC","Palermo","PA","","","37.7209","13.4344","4"],"90039":["IT","90039","Villabate","Sicilia","SC","Palermo","PA","","","38.0779","13.4428","4"],"90040":["IT","90040","Torretta","Sicilia","SC","Palermo","PA","","","38.1304","13.2355","4"],"90041":["IT","90041","Foce","Sicilia","SC","Palermo","PA","","","38.0512","13.0072","4"],"90042":["IT","90042","Borgetto","Sicilia","SC","Palermo","PA","","","38.0466","13.1407","4"],"90043":["IT","90043","Camporeale","Sicilia","SC","Palermo","PA","","","37.8861","13.1011","4"],"90044":["IT","90044","Villagrazia Di Carini","Sicilia","SC","Palermo","PA","","","38.1617","13.169","4"],"90045":["IT","90045","Cinisi","Sicilia","SC","Palermo","PA","","","38.1608","13.101","4"],"90046":["IT","90046","Poggio San Francesco","Sicilia","SC","Palermo","PA","","","38.0049","13.3415","3"],"90047":["IT","90047","Partinico","Sicilia","SC","Palermo","PA","","","38.0466","13.1179","4"],"90048":["IT","90048","San Giuseppe Jato","Sicilia","SC","Palermo","PA","","","37.9733","13.1889","4"],"90049":["IT","90049","Terrasini","Sicilia","SC","Palermo","PA","","","38.1462","13.0832","4"],"90100":["IT","90100","Palermo","Sicilia","SC","Palermo","PA","","","38.1321","13.3356","4"],"90121":["IT","90121","In Via Ammiraglio Cristodulo","Sicilia","SC","Palermo","PA","","","38.116","13.3178","3"],"90122":["IT","90122","Roccella Guarnaschelli","Sicilia","SC","Palermo","PA","","","38.1321","13.3356","3"],"90123":["IT","90123","Settecannoli","Sicilia","SC","Palermo","PA","","","38.1321","13.3356","3"],"90124":["IT","90124","In Via Brancaccio","Sicilia","SC","Palermo","PA","","","38.1321","13.3356","3"],"90125":["IT","90125","In Via Aloi","Sicilia","SC","Palermo","PA","","","38.1321","13.3356","3"],"90126":["IT","90126","Mezzomonreale Boccadifalco","Sicilia","SC","Palermo","PA","","","38.1321","13.3356","3"],"90127":["IT","90127","Palermo","Sicilia","SC","Palermo","PA","","","38.1321","13.3356","4"],"90128":["IT","90128","Palermo","Sicilia","SC","Palermo","PA","","","38.1321","13.3356","4"],"90129":["IT","90129","Palermo","Sicilia","SC","Palermo","PA","","","38.1321","13.3356","4"],"90131":["IT","90131","Palermo","Sicilia","SC","Palermo","PA","","","38.1321","13.3356","4"],"90132":["IT","90132","Palermo","Sicilia","SC","Palermo","PA","","","38.1321","13.3356","4"],"90133":["IT","90133","Palermo","Sicilia","SC","Palermo","PA","","","38.1321","13.3356","4"],"90134":["IT","90134","In Via Gioiamia","Sicilia","SC","Palermo","PA","","","38.1321","13.3356","3"],"90135":["IT","90135","Zisa","Sicilia","SC","Palermo","PA","","","38.1321","13.3356","3"],"90136":["IT","90136","Palermo","Sicilia","SC","Palermo","PA","","","38.1321","13.3356","4"],"90137":["IT","90137","Palermo","Sicilia","SC","Palermo","PA","","","38.1321","13.3356","4"],"90138":["IT","90138","Palermo","Sicilia","SC","Palermo","PA","","","38.1321","13.3356","4"],"90139":["IT","90139","Palermo","Sicilia","SC","Palermo","PA","","","38.1321","13.3356","4"],"90141":["IT","90141","Palermo","Sicilia","SC","Palermo","PA","","","38.1321","13.3356","4"],"90142":["IT","90142","Montepellegrino","Sicilia","SC","Palermo","PA","","","38.1321","13.3356","3"],"90143":["IT","90143","Palermo","Sicilia","SC","Palermo","PA","","","38.1321","13.3356","4"],"90144":["IT","90144","Palermo","Sicilia","SC","Palermo","PA","","","38.1321","13.3356","4"],"90145":["IT","90145","Palermo","Sicilia","SC","Palermo","PA","","","38.1321","13.3356","4"],"90146":["IT","90146","Pallavicino","Sicilia","SC","Palermo","PA","","","38.1321","13.3356","3"],"90147":["IT","90147","Tommaso Natale Sferracavallo","Sicilia","SC","Palermo","PA","","","38.1321","13.3356","3"],"90148":["IT","90148","Palermo","Sicilia","SC","Palermo","PA","","","38.1321","13.3356","4"],"90149":["IT","90149","Palermo","Sicilia","SC","Palermo","PA","","","38.1321","13.3356","4"],"90151":["IT","90151","Palermo","Sicilia","SC","Palermo","PA","","","38.1321","13.3356","4"]}